README
setup.py
Flask_Raptor.egg-info/PKG-INFO
Flask_Raptor.egg-info/SOURCES.txt
Flask_Raptor.egg-info/dependency_links.txt
Flask_Raptor.egg-info/not-zip-safe
Flask_Raptor.egg-info/requires.txt
Flask_Raptor.egg-info/top_level.txt
flask_raptor/__init__.py
flask_raptor/flask_raptor.py