Metadata-Version: 1.0
Name: Flask-Raptor
Version: 0.1
Summary: Raptor support for Flask
Home-page: http://github.com/dplepage/flask-raptor
Author: Dan Lepage
Author-email: dplepage@gmail.com
License: BSD
Platform: any
Classifier: Development Status :: 4 - Beta
Classifier: Environment :: Web Environment
Classifier: Intended Audience :: Developers
Classifier: License :: OSI Approved :: BSD License
Classifier: Operating System :: OS Independent
Classifier: Programming Language :: Python
Classifier: Topic :: Software Development :: Libraries :: Python Modules
